{"is_source_file": false, "format": "", "description": "", "external_files": [], "external_methods": [], "published": [], "classes": [], "methods": [], "calls": [], "search-terms": [], "state": 2, "file_id": 11, "knowledge_revision": 39, "git_revision": "74f297b9cbea771af5d2a6ed60b3f75aec0a3e05", "hash": "2da857e316d857be51b3813c6d51b5cd", "format-version": 4, "code-base-name": "notes_frontend", "filename": "notes_frontend/src/routes/styles.css", "revision_history": [{"39": "74f297b9cbea771af5d2a6ed60b3f75aec0a3e05"}]}